{
  "items": [
    {
      "type": "file",
      "ctime": 1744223841707,
      "path": "Scratchpads/HTTP.md"
    },
    {
      "type": "file",
      "ctime": 1744537912953,
      "path": "Scratchpads/Scratchpad - System Design.md"
    },
    {
      "type": "file",
      "ctime": 1744540770150,
      "path": "Notes/How to approach System Design.md"
    },
    {
      "type": "file",
      "ctime": 1744552248494,
      "path": "Mindmaps/System Design.md"
    },
    {
      "type": "file",
      "ctime": 1744552252069,
      "path": "Mindmaps/Backend.md"
    },
    {
      "type": "file",
      "ctime": 1747390432530,
      "path": "Notes/Message Queue.md"
    },
    {
      "type": "group",
      "ctime": 1749925099419,
      "items": [
        {
          "type": "group",
          "ctime": 1749925118822,
          "items": [
            {
              "type": "group",
              "ctime": 1749925118822,
              "items": [
                {
                  "type": "group",
                  "ctime": 1749925118822,
                  "items": [
                    {
                      "type": "file",
                      "ctime": 1749925139113,
                      "path": "Reference Notes/Leetcode/Data Structures and Algorithms/Arrays and Strings.md",
                      "subpath": "#^-"
                    },
                    {
                      "type": "group",
                      "ctime": 1749925118822,
                      "items": [],
                      "title": "Introduction"
                    },
                    {
                      "type": "file",
                      "ctime": 1749925139113,
                      "path": "Reference Notes/Leetcode/Data Structures and Algorithms/_note_Data Structures and Algorithms.md",
                      "subpath": "#^-"
                    }
                  ],
                  "title": "\\\\Data Structures and Algorithms"
                }
              ],
              "title": "\\\\Leetcode"
            }
          ],
          "title": "Reference Notes"
        }
      ],
      "title": "sortspec"
    }
  ]
}