{
  "main": {
    "id": "a93c96a744ff55e6",
    "type": "split",
    "children": [
      {
        "id": "6141e630b5745b1a",
        "type": "tabs",
        "children": [
          {
            "id": "a10942d1631f3e2d",
            "type": "leaf",
            "pinned": true,
            "state": {
              "type": "markdown",
              "state": {
                "file": "Course Notes/Github - donnemartin system-design-primer/--Table of Contents--.md",
                "mode": "source",
                "source": false
              },
              "pinned": true,
              "icon": "lucide-file",
              "title": "--Table of Contents--"
            }
          },
          {
            "id": "77bf4a099a4a8910",
            "type": "leaf",
            "state": {
              "type": "markdown",
              "state": {
                "file": "Spring/Spring.md",
                "mode": "source",
                "source": false
              },
              "icon": "lucide-file",
              "title": "Spring"
            }
          }
        ]
      }
    ],
    "direction": "vertical"
  },
  "left": {
    "id": "6f41992da3c7f59e",
    "type": "split",
    "children": [
      {
        "id": "7b7a61d934b5e312",
        "type": "tabs",
        "children": [
          {
            "id": "bd2714a80d3d3c1d",
            "type": "leaf",
            "state": {
              "type": "file-explorer",
              "state": {
                "sortOrder": "alphabetical"
              },
              "icon": "lucide-folder-closed",
              "title": "Files"
            }
          },
          {
            "id": "b0c2dedb11ea3190",
            "type": "leaf",
            "state": {
              "type": "search",
              "state": {
                "query": "",
                "matchingCase": false,
                "explainSearch": false,
                "collapseAll": false,
                "extraContext": false,
                "sortOrder": "alphabetical"
              },
              "icon": "lucide-search",
              "title": "Search"
            }
          },
          {
            "id": "0fc0c9c5268a5851",
            "type": "leaf",
            "state": {
              "type": "bookmarks",
              "state": {},
              "icon": "lucide-bookmark",
              "title": "Bookmarks"
            }
          }
        ]
      }
    ],
    "direction": "horizontal",
    "width": 293.0110321044922
  },
  "right": {
    "id": "2e5b03630ad99a9e",
    "type": "split",
    "children": [
      {
        "id": "893d8ad78ecdd498",
        "type": "tabs",
        "children": [
          {
            "id": "8f96f2b92bce22dd",
            "type": "leaf",
            "state": {
              "type": "backlink",
              "state": {
                "file": "Amazon Web Services/Services/Elastic Compute Cloud/Instance Metadata.md",
                "collapseAll": false,
                "extraContext": false,
                "sortOrder": "alphabetical",
                "showSearch": false,
                "searchQuery": "",
                "backlinkCollapsed": false,
                "unlinkedCollapsed": false
              },
              "icon": "links-coming-in",
              "title": "Backlinks for Instance Metadata"
            }
          },
          {
            "id": "b6ccd2f876a599ff",
            "type": "leaf",
            "state": {
              "type": "outgoing-link",
              "state": {
                "file": "Amazon Web Services/Services/Elastic Compute Cloud/Instance Metadata.md",
                "linksCollapsed": false,
                "unlinkedCollapsed": true
              },
              "icon": "links-going-out",
              "title": "Outgoing links from Instance Metadata"
            }
          },
          {
            "id": "e2c80372fbe8dfbc",
            "type": "leaf",
            "state": {
              "type": "tag",
              "state": {
                "sortOrder": "frequency",
                "useHierarchy": true
              },
              "icon": "lucide-tags",
              "title": "Tags"
            }
          },
          {
            "id": "d2667930fede267f",
            "type": "leaf",
            "state": {
              "type": "outline",
              "state": {
                "file": "Course Notes/Github - donnemartin system-design-primer/Application layer.md"
              },
              "icon": "lucide-list",
              "title": "Outline of Application layer"
            }
          },
          {
            "id": "6fb2c6e933107257",
            "type": "leaf",
            "state": {
              "type": "side-panel-control-view",
              "state": {},
              "icon": "viewIcon",
              "title": "Markdown-Autocomplete"
            }
          },
          {
            "id": "b7a897f0c88ab5ce",
            "type": "leaf",
            "state": {
              "type": "git-view",
              "state": {},
              "icon": "lucide-file",
              "title": "Plugin no longer active"
            }
          }
        ],
        "currentTab": 4
      }
    ],
    "direction": "horizontal",
    "width": 301,
    "collapsed": true
  },
  "left-ribbon": {
    "hiddenItems": {
      "switcher:Open quick switcher": false,
      "graph:Open graph view": false,
      "canvas:Create new canvas": false,
      "daily-notes:Open today's daily note": false,
      "templates:Insert template": false,
      "command-palette:Open command palette": false,
      "obsidian-markdown-formatting-assistant-plugin:Open Markdown Formatting Assistant": false,
      "omnisearch:Omnisearch": false,
      "open-vscode:VSCode": false,
      "table-editor-obsidian:Advanced Tables Toolbar": false,
      "obsidian-excalidraw-plugin:Create new drawing": false
    }
  },
  "active": "a10942d1631f3e2d",
  "lastOpenFiles": [
    "Spring/_Index_of_Spring.md",
    "Spring/--Table of Contents--.md",
    "Spring/Spring Boot.md",
    "Spring/Spring.md",
    "--Obsidian Template--/_Index_of_--Obsidian Template--.md",
    "--Personal Notes--/-- TODO --/_Index_of_-- TODO --.md",
    "--Personal Notes--/-- TODO --/Question Notes/_Index_of_Question Notes.md",
    "--Personal Notes--/Random/_Index_of_Random.md",
    "--Personal Notes--/_Index_of_--Personal Notes--.md",
    "Amazon Web Services/Accounts/Identity and Access Management (IAM)/Main Jobs/_Index_of_Main Jobs.md",
    "Amazon Web Services/Accounts/Identity and Access Management (IAM)/_Index_of_Identity and Access Management (IAM).md",
    "Amazon Web Services/Accounts/Identity and Access Management (IAM)/Types of IAM users/_Index_of_Types of IAM users.md",
    "Amazon Web Services/Accounts/_Index_of_Accounts.md",
    "Amazon Web Services/AWS Command Line Interface/_Index_of_AWS Command Line Interface.md",
    "Amazon Web Services/Fundamentals/_Index_of_Fundamentals.md",
    "Amazon Web Services/Exam/_Index_of_Exam.md",
    "Amazon Web Services/HA & Scaling/_Index_of_HA & Scaling.md",
    "Amazon Web Services/Global Content Delivery and Optimization/_Index_of_Global Content Delivery and Optimization.md",
    "Amazon Web Services/Local Zones/_Index_of_Local Zones.md",
    "Amazon Web Services/Machine Learning 101/_Index_of_Machine Learning 101.md",
    "Amazon Web Services/Images/_Index_of_Images.md",
    "Amazon Web Services/Serverless and Application Services/_Index_of_Serverless and Application Services.md",
    "Amazon Web Services/Services/API Gateway/_Index_of_API Gateway.md",
    "Amazon Web Services/Services/Appflow/_Index_of_Appflow.md",
    "Amazon Web Services/Services/Athena/_Index_of_Athena.md",
    "Amazon Web Services/Services/AWS Control Tower/_Index_of_AWS Control Tower.md",
    "Spring",
    "Quality Assurance",
    "Interview Preparation/Javascript",
    "Course Notes/Hussein Nasser/Udemy - Fundamentals of Backend Engineering",
    "Course Notes/Hussein Nasser",
    "Course Notes/Github - donnemartin system-design-primer",
    "Course Notes/Github - Learn Node.js Hardway",
    "Course Notes",
    "System Design",
    "--Attachments--",
    "Cloud Computing/Images/Pasted image 20221229142305.png",
    "Amazon Web Services/Images/Pasted image 20230707023334.png",
    "Amazon Web Services/Images/Pasted image 20230701150016.png",
    "Amazon Web Services/Images/Pasted image 20230701150230.png",
    "Amazon Web Services/Images/Pasted image 20230701150259.png",
    "Amazon Web Services/Images/Pasted image 20230701150051.png",
    "Amazon Web Services/Images/Pasted image 20230517042859.png",
    "Amazon Web Services/Images/Pasted image 20230517043342.png",
    "Amazon Web Services/Images/Pasted image 20230521153320.png",
    "Amazon Web Services/Images/Pasted image 20230517043205.png"
  ]
}